{
  "schema": "https://valaxy.site/schemas/food-map.v1.json",
  "schemaVersion": 1,
  "generator": {
    "name": "nocturne-archive-blog-food-map",
    "version": 1
  },
  "owner": {
    "name": "Nocturne Archive"
  },
  "site": {
    "name": "Nocturne Archive",
    "url": "https://blog.sphenicidition.top"
  },
  "generatedAt": "2026-05-27T12:47:49.184Z",
  "coordinateSystem": "GCJ-02",
  "spots": [
    {
      "id": "chengdu-mococo-mexican-restaurant",
      "name": "M'OCOCO墨西哥餐厅",
      "city": "成都",
      "address": "成都市金牛区上城天街成华西街299号5栋附107号",
      "lng": 104.071017,
      "lat": 30.684007,
      "coordinateSystem": "GCJ-02",
      "category": "墨西哥菜",
      "price": 55,
      "rating": 4.8,
      "recommend": [
        "柠檬黄油青口贝"
      ],
      "amapUrl": "https://surl.amap.com/fW48qJ8laCK",
      "source": {
        "type": "local",
        "id": "local",
        "name": "Local"
      }
    },
    {
      "id": "chengdu-rongcheng-shuangshuang-meiwa-fish",
      "name": "蓉城霜霜美娃鱼",
      "city": "成都",
      "address": "郫都区金怡巷85号",
      "lng": 103.95206540822981,
      "lat": 30.785646101310576,
      "coordinateSystem": "GCJ-02",
      "category": "自助餐",
      "price": 70,
      "rating": 5,
      "recommend": [
        "红油美娃"
      ],
      "amapUrl": "https://surl.amap.com/88T27OSkgd6",
      "source": {
        "type": "local",
        "id": "local",
        "name": "Local"
      }
    }
  ]
}
